coplot/__init__.py
coplot/plot_contours.py
coplot/plot_settings.py
coplot/plots.py
coplot/utils.py
coplot-0.2.0.data/data/README.txt
examples/contour_1D/README.txt
examples/contour_1D/plot_1d_1.py
examples/contour_1D/plot_1d_2.py
examples/contour_1D/plot_1d_3.py
examples/contour_2D/README.txt
examples/contour_2D/plot_2d_1.py
examples/contour_2D/plot_2d_2.py
examples/contour_2D/plot_2d_3.py
examples/contour_triangle/README.txt
examples/contour_triangle/plot_triangle_1.py
examples/contour_triangle/plot_triangle_2.py
examples/contour_triangle/plot_triangle_3.py
examples/contour_triangle/plot_triangle_4.py
coplot-0.2.0.dist-info/METADATA
coplot-0.2.0.dist-info/WHEEL
coplot-0.2.0.dist-info/top_level.txt
coplot-0.2.0.dist-info/RECORD
