Metadata-Version: 2.1
Name: coplot
Version: 0.2.0
Summary: A personal plotting library that commonly used in the research of cosmology and astrophysics.
Home-page: 
Author: Guojian Wang
Author-email: gjwang@mail.bnu.edu.cn
License: MIT
Keywords: pip,plot
Platform: any
